polyquery/__init__.py
polyquery/__metadata__.py
polyquery-0.1.0.dist-info/METADATA
polyquery-0.1.0.dist-info/WHEEL
polyquery-0.1.0.dist-info/licenses/LICENSE.txt
polyquery-0.1.0.dist-info/RECORD
